Workbook

Sheet Analysis
A1: SKU | B1: Product Name | C1: Category | D1: Total Units Sold (6mo) | E1: Avg Monthly Sales | F1: Revenue (NGN) | G1: COGS (NGN) | H1: Gross Profit (NGN) | I1: Stock on Hand | J1: Reorder Level | K1: Inventory Turnover Ratio | L1: Months of Stock Remaining | M1: Stock Status | N1: Revenue % of Total | O1: Cumulative Revenue % | P1: ABC Class | Q1: Dead Stock Flag
A2: ='Raw Data'!A2 -> SKU-1001 | B2: ='Raw Data'!B2 -> Lagoona Sneakers A1 | C2: ='Raw Data'!C2 -> Footwear | D2: =SUM('Raw Data'!K2:P2) -> 245 | E2: =D2/6 -> 40.833333 | F2: =D2*'Raw Data'!G2 -> 4221350 | G2: =D2*'Raw Data'!F2 -> 2775850 | H2: =F2-G2 -> 1445500 | I2: ='Raw Data'!H2 -> 24 | J2: ='Raw Data'!I2 -> 61 | K2: =IF(I2=0,0,D2/I2) -> 10.208333 | L2: =IF(E2=0,999,I2/E2) -> 0.5877551 | M2: =IF(D2=0,"Dead Stock",IF(I2<=J2,"Reorder Needed",IF(L2>6,"Overstocked","Healthy"))) -> Reorder Needed | N2: =F2/SUM($F$2:$F$151) -> 0.024044589 | O2: =SUMPRODUCT(($F$2:$F$151>=F2)*$F$2:$F$151)/SUM($F$2:$F$151) -> 0.20945765 | P2: =IF(O2<=0.8,"A",IF(O2<=0.95,"B","C")) -> A | Q2: =IF(D2=0,"Yes","No") -> No
A3: ='Raw Data'!A3 -> SKU-1003 | B3: ='Raw Data'!B3 -> Primecraft Sneakers F3 | C3: ='Raw Data'!C3 -> Footwear | D3: =SUM('Raw Data'!K3:P3) -> 111 | E3: =D3/6 -> 18.5 | F3: =D3*'Raw Data'!G3 -> 409590 | G3: =D3*'Raw Data'!F3 -> 249750 | H3: =F3-G3 -> 159840 | I3: ='Raw Data'!H3 -> 30 | J3: ='Raw Data'!I3 -> 27 | K3: =IF(I3=0,0,D3/I3) -> 3.7 | L3: =IF(E3=0,999,I3/E3) -> 1.6216216 | M3: =IF(D3=0,"Dead Stock",IF(I3<=J3,"Reorder Needed",IF(L3>6,"Overstocked","Healthy"))) -> Healthy | N3: =F3/SUM($F$2:$F$151) -> 0.0023330032 | O3: =SUMPRODUCT(($F$2:$F$151>=F3)*$F$2:$F$151)/SUM($F$2:$F$151) -> 0.94415345 | P3: =IF(O3<=0.8,"A",IF(O3<=0.95,"B","C")) -> B | Q3: =IF(D3=0,"Yes","No") -> No
A4: ='Raw Data'!A4 -> SKU-1004 | B4: ='Raw Data'!B4 -> Tide Sneakers F4 | C4: ='Raw Data'!C4 -> Footwear | D4: =SUM('Raw Data'!K4:P4) -> 261 | E4: =D4/6 -> 43.5 | F4: =D4*'Raw Data'!G4 -> 4544010 | G4: =D4*'Raw Data'!F4 -> 2349000 | H4: =F4-G4 -> 2195010 | I4: ='Raw Data'!H4 -> 50 | J4: ='Raw Data'!I4 -> 65 | K4: =IF(I4=0,0,D4/I4) -> 5.22 | L4: =IF(E4=0,999,I4/E4) -> 1.1494253 | M4: =IF(D4=0,"Dead Stock",IF(I4<=J4,"Reorder Needed",IF(L4>6,"Overstocked","Healthy"))) -> Reorder Needed | N4: =F4/SUM($F$2:$F$151) -> 0.025882443 | O4: =SUMPRODUCT(($F$2:$F$151>=F4)*$F$2:$F$151)/SUM($F$2:$F$151) -> 0.084548369 | P4: =IF(O4<=0.8,"A",IF(O4<=0.95,"B","C")) -> A | Q4: =IF(D4=0,"Yes","No") -> No
A5: ='Raw Data'!A5 -> SKU-1005 | B5: ='Raw Data'!B5 -> Coastline Sneakers F5 | C5: ='Raw Data'!C5 -> Footwear | D5: =SUM('Raw Data'!K5:P5) -> 1 | E5: =D5/6 -> 0.16666667 | F5: =D5*'Raw Data'!G5 -> 5810 | G5: =D5*'Raw Data'!F5 -> 3770 | H5: =F5-G5 -> 2040 | I5: ='Raw Data'!H5 -> 117 | J5: ='Raw Data'!I5 -> 5 | K5: =IF(I5=0,0,D5/I5) -> 0.0085470085 | L5: =IF(E5=0,999,I5/E5) -> 702 | M5: =IF(D5=0,"Dead Stock",IF(I5<=J5,"Reorder Needed",IF(L5>6,"Overstocked","Healthy"))) -> Overstocked | N5: =F5/SUM($F$2:$F$151) -> 3.3093456e-05 | O5: =SUMPRODUCT(($F$2:$F$151>=F5)*$F$2:$F$151)/SUM($F$2:$F$151) -> 1 | P5: =IF(O5<=0.8,"A",IF(O5<=0.95,"B","C")) -> C | Q5: =IF(D5=0,"Yes","No") -> No
A6: ='Raw Data'!A6 -> SKU-1006 | B6: ='Raw Data'!B6 -> Primecraft Sneakers C6 | C6: ='Raw Data'!C6 -> Footwear | D6: =SUM('Raw Data'!K6:P6) -> 1 | E6: =D6/6 -> 0.16666667 | F6: =D6*'Raw Data'!G6 -> 11360 | G6: =D6*'Raw Data'!F6 -> 7360 | H6: =F6-G6 -> 4000 | I6: ='Raw Data'!H6 -> 127 | J6: ='Raw Data'!I6 -> 5 | K6: =IF(I6=0,0,D6/I6) -> 0.0078740157 | L6: =IF(E6=0,999,I6/E6) -> 762 | M6: =IF(D6=0,"Dead Stock",IF(I6<=J6,"Reorder Needed",IF(L6>6,"Overstocked","Healthy"))) -> Overstocked | N6: =F6/SUM($F$2:$F$151) -> 6.4705966e-05 | O6: =SUMPRODUCT(($F$2:$F$151>=F6)*$F$2:$F$151)/SUM($F$2:$F$151) -> 0.99981192 | P6: =IF(O6<=0.8,"A",IF(O6<=0.95,"B","C")) -> C | Q6: =IF(D6=0,"Yes","No") -> No
A7: ='Raw Data'!A7 -> SKU-1010 | B7: ='Raw Data'!B7 -> Zenith Sneakers F10 | C7: ='Raw Data'!C7 -> Footwear | D7: =SUM('Raw Data'!K7:P7) -> 113 | E7: =D7/6 -> 18.833333 | F7: =D7*'Raw Data'!G7 -> 455390 | G7: =D7*'Raw Data'!F7 -> 268940 | H7: =F7-G7 -> 186450 | I7: ='Raw Data'!H7 -> 100 | J7: ='Raw Data'!I7 -> 28 | K7: =IF(I7=0,0,D7/I7) -> 1.13 | L7: =IF(E7=0,999,I7/E7) -> 5.3097345 | M7: =IF(D7=0,"Dead Stock",IF(I7<=J7,"Reorder Needed",IF(L7>6,"Overstocked","Healthy"))) -> Healthy | N7: =F7/SUM($F$2:$F$151) -> 0.0025938776 | O7: =SUMPRODUCT(($F$2:$F$151>=F7)*$F$2:$F$151)/SUM($F$2:$F$151) -> 0.93197706 | P7: =IF(O7<=0.8,"A",IF(O7<=0.95,"B","C")) -> B | Q7: =IF(D7=0,"Yes","No") -> No
A8: ='Raw Data'!A8 -> SKU-1011 | B8: ='Raw Data'!B8 -> Primecraft Sandals C1 | C8: ='Raw Data'!C8 -> Footwear | D8: =SUM('Raw Data'!K8:P8) -> 1 | E8: =D8/6 -> 0.16666667 | F8: =D8*'Raw Data'!G8 -> 8830 | G8: =D8*'Raw Data'!F8 -> 6110 | H8: =F8-G8 -> 2720 | I8: ='Raw Data'!H8 -> 116 | J8: ='Raw Data'!I8 -> 5 | K8: =IF(I8=0,0,D8/I8) -> 0.0086206897 | L8: =IF(E8=0,999,I8/E8) -> 696 | M8: =IF(D8=0,"Dead Stock",IF(I8<=J8,"Reorder Needed",IF(L8>6,"Overstocked","Healthy"))) -> Overstocked | N8: =F8/SUM($F$2:$F$151) -> 5.0295218e-05 | O8: =SUMPRODUCT(($F$2:$F$151>=F8)*$F$2:$F$151)/SUM($F$2:$F$151) -> 0.99992031 | P8: =IF(O8<=0.8,"A",IF(O8<=0.95,"B","C")) -> C | Q8: =IF(D8=0,"Yes","No") -> No
A9: ='Raw Data'!A9 -> SKU-1013 | B9: ='Raw Data'!B9 -> Nova Sandals H3 | C9: ='Raw Data'!C9 -> Footwear | D9: =SUM('Raw Data'!K9:P9) -> 62 | E9: =D9/6 -> 10.333333 | F9: =D9*'Raw Data'!G9 -> 1279680 | G9: =D9*'Raw Data'!F9 -> 883500 | H9: =F9-G9 -> 396180 | I9: ='Raw Data'!H9 -> 71 | J9: ='Raw Data'!I9 -> 15 | K9: =IF(I9=0,0,D9/I9) -> 0.87323944 | L9: =IF(E9=0,999,I9/E9) -> 6.8709677 | M9: =IF(D9=0,"Dead Stock",IF(I9<=J9,"Reorder Needed",IF(L9>6,"Overstocked","Healthy"))) -> Overstocked | N9: =F9/SUM($F$2:$F$151) -> 0.0072889903 | O9: =SUMPRODUCT(($F$2:$F$151>=F9)*$F$2:$F$151)/SUM($F$2:$F$151) -> 0.73271515 | P9: =IF(O9<=0.8,"A",IF(O9<=0.95,"B","C")) -> A | Q9: =IF(D9=0,"Yes","No") -> No
A10: ='Raw Data'!A10 -> SKU-1014 | B10: ='Raw Data'!B10 -> Bravo Sandals H4 | C10: ='Raw Data'!C10 -> Footwear | D10: =SUM('Raw Data'!K10:P10) -> 79 | E10: =D10/6 -> 13.166667 | F10: =D10*'Raw Data'!G10 -> 299410 | G10: =D10*'Raw Data'!F10 -> 199080 | H10: =F10-G10 -> 100330 | I10: ='Raw Data'!H10 -> 24 | J10: ='Raw Data'!I10 -> 19 | K10: =IF(I10=0,0,D10/I10) -> 3.2916667 | L10: =IF(E10=0,999,I10/E10) -> 1.8227848 | M10: =IF(D10=0,"Dead Stock",IF(I10<=J10,"Reorder Needed",IF(L10>6,"Overstocked","Healthy"))) -> Healthy | N10: =F10/SUM($F$2:$F$151) -> 0.0017054237 | O10: =SUMPRODUCT(($F$2:$F$151>=F10)*$F$2:$F$151)/SUM($F$2:$F$151) -> 0.96943714 | P10: =IF(O10<=0.8,"A",IF(O10<=0.95,"B","C")) -> C | Q10: =IF(D10=0,"Yes","No") -> No
A11: ='Raw Data'!A11 -> SKU-1015 | B11: ='Raw Data'!B11 -> Bravo Sandals D5 | C11: ='Raw Data'!C11 -> Footwear | D11: =SUM('Raw Data'!K11:P11) -> 65 | E11: =D11/6 -> 10.833333 | F11: =D11*'Raw Data'!G11 -> 536250 | G11: =D11*'Raw Data'!F11 -> 308750 | H11: =F11-G11 -> 227500 | I11: ='Raw Data'!H11 -> 32 | J11: ='Raw Data'!I11 -> 16 | K11: =IF(I11=0,0,D11/I11) -> 2.03125 | L11: =IF(E11=0,999,I11/E11) -> 2.9538462 | M11: =IF(D11=0,"Dead Stock",IF(I11<=J11,"Reorder Needed",IF(L11>6,"Overstocked","Healthy"))) -> Healthy | N11: =F11/SUM($F$2:$F$151) -> 0.0030544519 | O11: =SUMPRODUCT(($F$2:$F$151>=F11)*$F$2:$F$151)/SUM($F$2:$F$151) -> 0.91781146 | P11: =IF(O11<=0.8,"A",IF(O11<=0.95,"B","C")) -> B | Q11: =IF(D11=0,"Yes","No") -> No
A12: ='Raw Data'!A12 -> SKU-1016 | B12: ='Raw Data'!B12 -> Coastline Sandals G6 | C12: ='Raw Data'!C12 -> Footwear | D12: =SUM('Raw Data'!K12:P12) -> 235 | E12: =D12/6 -> 39.166667 | F12: =D12*'Raw Data'!G12 -> 3240650 | G12: =D12*'Raw Data'!F12 -> 1560400 | H12: =F12-G12 -> 1680250 | I12: ='Raw Data'!H12 -> 22 | J12: ='Raw Data'!I12 -> 58 | K12: =IF(I12=0,0,D12/I12) -> 10.681818 | L12: =IF(E12=0,999,I12/E12) -> 0.56170213 | M12: =IF(D12=0,"Dead Stock",IF(I12<=J12,"Reorder Needed",IF(L12>6,"Overstocked","Healthy"))) -> Reorder Needed | N12: =F12/SUM($F$2:$F$151) -> 0.018458573 | O12: =SUMPRODUCT(($F$2:$F$151>=F12)*$F$2:$F$151)/SUM($F$2:$F$151) -> 0.31452368 | P12: =IF(O12<=0.8,"A",IF(O12<=0.95,"B","C")) -> A | Q12: =IF(D12=0,"Yes","No") -> No
A13: ='Raw Data'!A13 -> SKU-1017 | B13: ='Raw Data'!B13 -> Mela Sandals C7 | C13: ='Raw Data'!C13 -> Footwear | D13: =SUM('Raw Data'!K13:P13) -> 113 | E13: =D13/6 -> 18.833333 | F13: =D13*'Raw Data'!G13 -> 1189890 | G13: =D13*'Raw Data'!F13 -> 767270 | H13: =F13-G13 -> 422620 | I13: ='Raw Data'!H13 -> 21 | J13: ='Raw Data'!I13 -> 28 | K13: =IF(I13=0,0,D13/I13) -> 5.3809524 | L13: =IF(E13=0,999,I13/E13) -> 1.1150442 | M13: =IF(D13=0,"Dead Stock",IF(I13<=J13,"Reorder Needed",IF(L13>6,"Overstocked","Healthy"))) -> Reorder Needed | N13: =F13/SUM($F$2:$F$151) -> 0.0067775512 | O13: =SUMPRODUCT(($F$2:$F$151>=F13)*$F$2:$F$151)/SUM($F$2:$F$151) -> 0.7678015 | P13: =IF(O13<=0.8,"A",IF(O13<=0.95,"B","C")) -> A | Q13: =IF(D13=0,"Yes","No") -> No
... A151: ='Raw Data'!A151 -> SKU-1222 | B151: ='Raw Data'!B151 -> Coastline Wristwatch G8 | C151: ='Raw Data'!C151 -> Accessories | D151: =SUM('Raw Data'!K151:P151) -> 83 | E151: =D151/6 -> 13.833333 | F151: =D151*'Raw Data'!G151 -> 1282350 | G151: =D151*'Raw Data'!F151 -> 671470 | H151: =F151-G151 -> 610880 | I151: ='Raw Data'!H151 -> 79 | J151: ='Raw Data'!I151 -> 20 | K151: =IF(I151=0,0,D151/I151) -> 1.0506329 | L151: =IF(E151=0,999,I151/E151) -> 5.7108434 | M151: =IF(D151=0,"Dead Stock",IF(I151<=J151,"Reorder Needed",IF(L151>6,"Overstocked","Healthy"))) -> Healthy | N151: =F151/SUM($F$2:$F$151) -> 0.0073041985 | O151: =SUMPRODUCT(($F$2:$F$151>=F151)*$F$2:$F$151)/SUM($F$2:$F$151) -> 0.71813136 | P151: =IF(O151<=0.8,"A",IF(O151<=0.95,"B","C")) -> A | Q151: =IF(D151=0,"Yes","No") -> No

Sheet Raw Data
A1: SKU | B1: Product Name | C1: Category | D1: Brand | E1: Supplier | F1: Cost Price (NGN) | G1: Selling Price (NGN) | H1: Stock on Hand (units) | I1: Reorder Level (units) | J1: Lead Time (days) | K1: Sales M1 | L1: Sales M2 | M1: Sales M3 | N1: Sales M4 | O1: Sales M5 | P1: Sales M6
A2: SKU-1001 | B2: Lagoona Sneakers A1 | C2: Footwear | D2: Lagoona | E2: Naija Trade Co | F2: 11330 | G2: 17230 | H2: 24 | I2: 61 | J2: 21 | K2: 50 | L2: 47 | M2: 29 | N2: 36 | O2: 43 | P2: 40
A3: SKU-1003 | B3: Primecraft Sneakers F3 | C3: Footwear | D3: Primecraft | E3: Greenline Supplies | F3: 2250 | G3: 3690 | H3: 30 | I3: 27 | J3: 21 | K3: 12 | L3: 18 | M3: 20 | N3: 16 | O3: 23 | P3: 22
A4: SKU-1004 | B4: Tide Sneakers F4 | C4: Footwear | D4: Tide | E4: Apex Distributors | F4: 9000 | G4: 17410 | H4: 50 | I4: 65 | J4: 10 | K4: 40 | L4: 46 | M4: 45 | N4: 42 | O4: 45 | P4: 43
A5: SKU-1005 | B5: Coastline Sneakers F5 | C5: Footwear | D5: Coastline | E5: Naija Trade Co | F5: 3770 | G5: 5810 | H5: 117 | I5: 5 | J5: 7 | K5: 0 | L5: 0 | M5: 1 | N5: 0 | O5: 0 | P5: 0
A6: SKU-1006 | B6: Primecraft Sneakers C6 | C6: Footwear | D6: Primecraft | E6: Lagos Wholesale Hub | F6: 7360 | G6: 11360 | H6: 127 | I6: 5 | J6: 10 | K6: 0 | L6: 0 | M6: 1 | N6: 0 | O6: 0 | P6: 0
A7: SKU-1010 | B7: Zenith Sneakers F10 | C7: Footwear | D7: Zenith | E7: Naija Trade Co | F7: 2380 | G7: 4030 | H7: 100 | I7: 28 | J7: 10 | K7: 24 | L7: 12 | M7: 14 | N7: 20 | O7: 19 | P7: 24
A8: SKU-1011 | B8: Primecraft Sandals C1 | C8: Footwear | D8: Primecraft | E8: Coastal Imports | F8: 6110 | G8: 8830 | H8: 116 | I8: 5 | J8: 10 | K8: 0 | L8: 0 | M8: 1 | N8: 0 | O8: 0 | P8: 0
A9: SKU-1013 | B9: Nova Sandals H3 | C9: Footwear | D9: Nova | E9: Coastal Imports | F9: 14250 | G9: 20640 | H9: 71 | I9: 15 | J9: 10 | K9: 4 | L9: 6 | M9: 22 | N9: 11 | O9: 12 | P9: 7
A10: SKU-1014 | B10: Bravo Sandals H4 | C10: Footwear | D10: Bravo | E10: Lagos Wholesale Hub | F10: 2520 | G10: 3790 | H10: 24 | I10: 19 | J10: 10 | K10: 11 | L10: 13 | M10: 15 | N10: 16 | O10: 12 | P10: 12
A11: SKU-1015 | B11: Bravo Sandals D5 | C11: Footwear | D11: Bravo | E11: Coastal Imports | F11: 4750 | G11: 8250 | H11: 32 | I11: 16 | J11: 5 | K11: 13 | L11: 4 | M11: 11 | N11: 13 | O11: 9 | P11: 15
A12: SKU-1016 | B12: Coastline Sandals G6 | C12: Footwear | D12: Coastline | E12: Naija Trade Co | F12: 6640 | G12: 13790 | H12: 22 | I12: 58 | J12: 7 | K12: 33 | L12: 30 | M12: 51 | N12: 44 | O12: 41 | P12: 36
A13: SKU-1017 | B13: Mela Sandals C7 | C13: Footwear | D13: Mela | E13: Apex Distributors | F13: 6790 | G13: 10530 | H13: 21 | I13: 28 | J13: 5 | K13: 19 | L13: 12 | M13: 19 | N13: 10 | O13: 33 | P13: 20
... A151: SKU-1222 | B151: Coastline Wristwatch G8 | C151: Accessories | D151: Coastline | E151: Apex Distributors | F151: 8090 | G151: 15450 | H151: 79 | I151: 20 | J151: 5 | K151: 16 | L151: 14 | M151: 10 | N151: 18 | O151: 14 | P151: 11
